cafqa/__init__.py
cafqa/circuit_manipulation.py
cafqa/main.py
cafqa/vqe_experiment.py
cafqa/vqe_helpers.py
cafqa-0.1.0.dist-info/METADATA
cafqa-0.1.0.dist-info/WHEEL
cafqa-0.1.0.dist-info/RECORD
