Metadata-Version: 2.4
Name: cafqa
Version: 0.1.0
Summary: CAFQA: A classical simulation bootstrap for variational quantum algorithms
Project-URL: Paper, https://arxiv.org/abs/2202.12924
Project-URL: Homepage, https://github.com/your-repo/cafqa
Project-URL: Repository, https://github.com/your-repo/cafqa
Author: Gokul Subramanian Ravi, Pranav Gokhale, Yi Ding, William M. Kirby, Kaitlin N. Smith, Jonathan M. Baker, Peter J. Love, Henry Hoffmann, Kenneth R. Brown, Frederic T. Chong
License: MIT
Keywords: Clifford gates,NISQ,VQE,ansatz initialization,quantum chemistry,quantum computing,quantum simulation,variational quantum algorithms
Classifier: Development Status :: 4 - Beta
Classifier: Intended Audience :: Science/Research
Classifier: License :: OSI Approved :: MIT License
Classifier: Programming Language :: Python :: 3
Classifier: Programming Language :: Python :: 3.12
Classifier: Topic :: Scientific/Engineering :: Chemistry
Classifier: Topic :: Scientific/Engineering :: Physics
Requires-Python: >=3.12
Requires-Dist: jupyter>=1.1.1
Requires-Dist: pyscf>=2.9.0
Requires-Dist: qiskit-aer>=0.17.1
Requires-Dist: qiskit-ibm-runtime>=0.35.0
Requires-Dist: qiskit-nature>=0.7.2
Requires-Dist: qiskit==1.2.1
Requires-Dist: scikit-quant>=0.8.2
Requires-Dist: stim>=1.15.0
Provides-Extra: all
Requires-Dist: hypermapper; extra == 'all'
Provides-Extra: cafqa
Requires-Dist: hypermapper; extra == 'cafqa'
